smart_knn/__init__.py
smart_knn/adaptive_k.py
smart_knn/base_knn.py
smart_knn/data_processing.py
smart_knn/distance.py
smart_knn/evaluation.py
smart_knn/prototypes.py
smart_knn/signatures.py
smart_knn/utils.py
smart_knn/weight_learning.py
smart_knn/backends/__init__.py
smart_knn/backends/brute_backend.py
smart_knn/backends/perf_backend.py
smart_knn-0.2.1.dist-info/licenses/LICENSE
smart_knn-0.2.1.dist-info/METADATA
smart_knn-0.2.1.dist-info/WHEEL
smart_knn-0.2.1.dist-info/top_level.txt
smart_knn-0.2.1.dist-info/RECORD
