Metadata-Version: 2.4
Name: smart-knn
Version: 0.2.1
Summary: A modern, weighted k-nearest neighbors algorithm with learned feature importance and fast CPU inference.
Author-email: Jashwanth Thatipamula <thatipamulajashwanthgoud@gmail.com>
License: MIT
Project-URL: Homepage, https://github.com/thatipamula-jashwanth/smart-knn
Project-URL: Documentation, https://thatipamula-jashwanth.github.io/SmartEco/
Project-URL: Repository, https://github.com/thatipamula-jashwanth/smart-knn
Project-URL: Issues, https://github.com/thatipamula-jashwanth/smart-knn/issues
Keywords: machine-learning,knn,nearest-neighbors,weighted-knn,interpretable-ml,cpu-ml,fast-inference,numba,regression,classification
Classifier: Development Status :: 4 - Beta
Classifier: Intended Audience :: Developers
Classifier: Intended Audience :: Science/Research
Classifier: License :: OSI Approved :: MIT License
Classifier: Operating System :: OS Independent
Classifier: Programming Language :: Python :: 3
Classifier: Programming Language :: Python :: 3.9
Classifier: Programming Language :: Python :: 3.10
Classifier: Programming Language :: Python :: 3.11
Classifier: Programming Language :: Python :: 3.12
Classifier: Topic :: Scientific/Engineering :: Artificial Intelligence
Requires-Python: >=3.9
License-File: LICENSE
Requires-Dist: numpy>=1.22
Requires-Dist: scikit-learn>=1.2
Requires-Dist: joblib>=1.2
Requires-Dist: numba>=0.60
Requires-Dist: faiss-cpu>=1.8.0
Dynamic: license-file
